<?xml version="1.0" encoding="UTF-8" standalone="no"?>
<preflight name="457634.pdf">
  <executionTimeMS>2654</executionTimeMS>
  <isValid type="PDF/A1-b">false</isValid>
  <errors count="3015">
    <error count="1">
      <code>7.1.1</code>
      <details>Error on MetaData, No type defined for {http://ns.adobe.com/xap/1.0/mm/}Manifest</details>
    </error>
    <error count="2">
      <code>3.1.6</code>
      <details>Invalid Font definition, Width of the character "0" in the font program "ArialMT"is inconsistent with the width in the PDF dictionary.</details>
    </error>
    <error count="2">
      <code>3.1.6</code>
      <details>Invalid Font definition, Width of the character "5" in the font program "ArialMT"is inconsistent with the width in the PDF dictionary.</details>
    </error>
    <error count="2">
      <code>3.1.6</code>
      <details>Invalid Font definition, Width of the character "4" in the font program "ArialMT"is inconsistent with the width in the PDF dictionary.</details>
    </error>
    <error count="9">
      <code>3.1.6</code>
      <details>Invalid Font definition, Width of the character "14" in the font program "ArialMT"is inconsistent with the width in the PDF dictionary.</details>
    </error>
    <error count="6">
      <code>3.1.6</code>
      <details>Invalid Font definition, Width of the character "8" in the font program "ArialMT"is inconsistent with the width in the PDF dictionary.</details>
    </error>
    <error count="12">
      <code>3.1.6</code>
      <details>Invalid Font definition, Width of the character "13" in the font program "ArialMT"is inconsistent with the width in the PDF dictionary.</details>
    </error>
    <error count="6">
      <code>3.1.6</code>
      <details>Invalid Font definition, Width of the character "6" in the font program "ArialMT"is inconsistent with the width in the PDF dictionary.</details>
    </error>
    <error count="7">
      <code>3.1.6</code>
      <details>Invalid Font definition, Width of the character "11" in the font program "ArialMT"is inconsistent with the width in the PDF dictionary.</details>
    </error>
    <error count="7">
      <code>3.1.6</code>
      <details>Invalid Font definition, Width of the character "7" in the font program "ArialMT"is inconsistent with the width in the PDF dictionary.</details>
    </error>
    <error count="19">
      <code>3.1.6</code>
      <details>Invalid Font definition, Width of the character "12" in the font program "ArialMT"is inconsistent with the width in the PDF dictionary.</details>
    </error>
    <error count="25">
      <code>3.1.6</code>
      <details>Invalid Font definition, Width of the character "10" in the font program "ArialMT"is inconsistent with the width in the PDF dictionary.</details>
    </error>
    <error count="4">
      <code>3.1.6</code>
      <details>Invalid Font definition, Width of the character "9" in the font program "ArialMT"is inconsistent with the width in the PDF dictionary.</details>
    </error>
    <error count="19">
      <code>3.1.6</code>
      <details>Invalid Font definition, Width of the character "1" in the font program "ArialMT"is inconsistent with the width in the PDF dictionary.</details>
    </error>
    <error count="7">
      <code>3.1.6</code>
      <details>Invalid Font definition, Width of the character "2" in the font program "ArialMT"is inconsistent with the width in the PDF dictionary.</details>
    </error>
    <error count="1">
      <code>3.1.6</code>
      <details>Invalid Font definition, Width of the character "3" in the font program "ArialMT"is inconsistent with the width in the PDF dictionary.</details>
    </error>
    <error count="1">
      <code>3.1.6</code>
      <details>Invalid Font definition, Width of the character "0" in the font program "Arial-BoldMT"is inconsistent with the width in the PDF dictionary.</details>
    </error>
    <error count="2">
      <code>3.1.6</code>
      <details>Invalid Font definition, Width of the character "9" in the font program "Arial-BoldMT"is inconsistent with the width in the PDF dictionary.</details>
    </error>
    <error count="1">
      <code>3.1.6</code>
      <details>Invalid Font definition, Width of the character "25" in the font program "Arial-BoldMT"is inconsistent with the width in the PDF dictionary.</details>
    </error>
    <error count="1">
      <code>3.1.6</code>
      <details>Invalid Font definition, Width of the character "11" in the font program "Arial-BoldMT"is inconsistent with the width in the PDF dictionary.</details>
    </error>
    <error count="1">
      <code>3.1.6</code>
      <details>Invalid Font definition, Width of the character "2" in the font program "Arial-BoldMT"is inconsistent with the width in the PDF dictionary.</details>
    </error>
    <error count="1">
      <code>3.1.6</code>
      <details>Invalid Font definition, Width of the character "5" in the font program "Arial-BoldMT"is inconsistent with the width in the PDF dictionary.</details>
    </error>
    <error count="1">
      <code>3.1.6</code>
      <details>Invalid Font definition, Width of the character "4" in the font program "Arial-BoldMT"is inconsistent with the width in the PDF dictionary.</details>
    </error>
    <error count="1">
      <code>3.1.6</code>
      <details>Invalid Font definition, Width of the character "3" in the font program "Arial-BoldMT"is inconsistent with the width in the PDF dictionary.</details>
    </error>
    <error count="1">
      <code>3.1.6</code>
      <details>Invalid Font definition, Width of the character "16" in the font program "Arial-BoldMT"is inconsistent with the width in the PDF dictionary.</details>
    </error>
    <error count="1">
      <code>3.1.6</code>
      <details>Invalid Font definition, Width of the character "20" in the font program "Arial-BoldMT"is inconsistent with the width in the PDF dictionary.</details>
    </error>
    <error count="1">
      <code>3.1.6</code>
      <details>Invalid Font definition, Width of the character "15" in the font program "Arial-BoldMT"is inconsistent with the width in the PDF dictionary.</details>
    </error>
    <error count="1">
      <code>3.1.6</code>
      <details>Invalid Font definition, Width of the character "10" in the font program "Arial-BoldMT"is inconsistent with the width in the PDF dictionary.</details>
    </error>
    <error count="1">
      <code>3.1.6</code>
      <details>Invalid Font definition, Width of the character "29" in the font program "Arial-BoldMT"is inconsistent with the width in the PDF dictionary.</details>
    </error>
    <error count="1">
      <code>3.1.6</code>
      <details>Invalid Font definition, Width of the character "8" in the font program "Arial-BoldMT"is inconsistent with the width in the PDF dictionary.</details>
    </error>
    <error count="1">
      <code>3.1.6</code>
      <details>Invalid Font definition, Width of the character "18" in the font program "Arial-BoldMT"is inconsistent with the width in the PDF dictionary.</details>
    </error>
    <error count="1">
      <code>3.1.6</code>
      <details>Invalid Font definition, Width of the character "28" in the font program "Arial-BoldMT"is inconsistent with the width in the PDF dictionary.</details>
    </error>
    <error count="1">
      <code>3.1.6</code>
      <details>Invalid Font definition, Width of the character "27" in the font program "Arial-BoldMT"is inconsistent with the width in the PDF dictionary.</details>
    </error>
    <error count="2">
      <code>3.1.6</code>
      <details>Invalid Font definition, Width of the character "23" in the font program "Arial-BoldMT"is inconsistent with the width in the PDF dictionary.</details>
    </error>
    <error count="1">
      <code>3.1.6</code>
      <details>Invalid Font definition, Width of the character "14" in the font program "Arial-BoldMT"is inconsistent with the width in the PDF dictionary.</details>
    </error>
    <error count="2">
      <code>3.1.6</code>
      <details>Invalid Font definition, Width of the character "21" in the font program "Arial-BoldMT"is inconsistent with the width in the PDF dictionary.</details>
    </error>
    <error count="3">
      <code>3.1.6</code>
      <details>Invalid Font definition, Width of the character "7" in the font program "Arial-BoldMT"is inconsistent with the width in the PDF dictionary.</details>
    </error>
    <error count="6">
      <code>3.1.6</code>
      <details>Invalid Font definition, Width of the character "24" in the font program "Arial-BoldMT"is inconsistent with the width in the PDF dictionary.</details>
    </error>
    <error count="4">
      <code>3.1.6</code>
      <details>Invalid Font definition, Width of the character "26" in the font program "Arial-BoldMT"is inconsistent with the width in the PDF dictionary.</details>
    </error>
    <error count="5">
      <code>3.1.6</code>
      <details>Invalid Font definition, Width of the character "13" in the font program "Arial-BoldMT"is inconsistent with the width in the PDF dictionary.</details>
    </error>
    <error count="1">
      <code>3.1.6</code>
      <details>Invalid Font definition, Width of the character "12" in the font program "Arial-BoldMT"is inconsistent with the width in the PDF dictionary.</details>
    </error>
    <error count="4">
      <code>3.1.6</code>
      <details>Invalid Font definition, Width of the character "19" in the font program "Arial-BoldMT"is inconsistent with the width in the PDF dictionary.</details>
    </error>
    <error count="11">
      <code>3.1.6</code>
      <details>Invalid Font definition, Width of the character "1" in the font program "Arial-BoldMT"is inconsistent with the width in the PDF dictionary.</details>
    </error>
    <error count="1">
      <code>3.1.6</code>
      <details>Invalid Font definition, Width of the character "30" in the font program "Arial-BoldMT"is inconsistent with the width in the PDF dictionary.</details>
    </error>
    <error count="4">
      <code>3.1.6</code>
      <details>Invalid Font definition, Width of the character "22" in the font program "Arial-BoldMT"is inconsistent with the width in the PDF dictionary.</details>
    </error>
    <error count="9">
      <code>3.1.6</code>
      <details>Invalid Font definition, Width of the character "17" in the font program "Arial-BoldMT"is inconsistent with the width in the PDF dictionary.</details>
    </error>
    <error count="1">
      <code>3.1.6</code>
      <details>Invalid Font definition, Width of the character "6" in the font program "Arial-BoldMT"is inconsistent with the width in the PDF dictionary.</details>
    </error>
    <error count="6">
      <code>3.1.9</code>
      <details>Invalid Font definition</details>
    </error>
    <error count="1579">
      <code>1.2.1</code>
      <details>Body Syntax error, Single space expected</details>
    </error>
    <error count="1">
      <code>1.4.6</code>
      <details>Trailer Syntax error, ID is different in the first and the last trailer</details>
    </error>
    <error count="40">
      <code>3.1.11</code>
      <details>Invalid Font definition, The CIDSet entry is missing for the Composite Subset</details>
    </error>
    <error count="6">
      <code>2.4.3</code>
      <details>Invalid Color space, The operator "f" can't be used without Color Profile</details>
    </error>
    <error count="4">
      <code>2.4.3</code>
      <details>Invalid Color space, The operator "g" can't be used without Color Profile</details>
    </error>
    <error count="925">
      <code>2.4.3</code>
      <details>Invalid Color space, The operator "G" can't be used without Color Profile</details>
    </error>
    <error count="98">
      <code>2.4.3</code>
      <details>Invalid Color space, The operator "f*" can't be used without Color Profile</details>
    </error>
    <error count="6">
      <code>2.4.3</code>
      <details>Invalid Color space, DestOutputProfile is missing</details>
    </error>
    <error count="40">
      <code>2.4.1</code>
      <details>Invalid Color space, The operator "RG" can't be used with CMYK Profile</details>
    </error>
    <error count="109">
      <code>2.4.1</code>
      <details>Invalid Color space, The operator "rg" can't be used with CMYK Profile</details>
    </error>
  </errors>
</preflight>
