<?xml version="1.0" encoding="UTF-8" standalone="no"?>
<preflight name="319905.pdf">
  <executionTimeMS>2083</executionTimeMS>
  <isValid type="PDF/A1-b">false</isValid>
  <errors count="98">
    <error count="6">
      <code>3.1.5</code>
      <details>Invalid Font definition, The Encoding should be missing for the Symbolic TTF</details>
    </error>
    <error count="4">
      <code>3.1.6</code>
      <details>Invalid Font definition, Width of the character "48" in the font program "NNHDHP+Helvetica"is inconsistent with the width in the PDF dictionary.</details>
    </error>
    <error count="2">
      <code>3.1.6</code>
      <details>Invalid Font definition, Width of the character "118" in the font program "NNHDHP+Helvetica"is inconsistent with the width in the PDF dictionary.</details>
    </error>
    <error count="2">
      <code>3.1.6</code>
      <details>Invalid Font definition, Width of the character "76" in the font program "NNHDHP+Helvetica"is inconsistent with the width in the PDF dictionary.</details>
    </error>
    <error count="4">
      <code>3.1.6</code>
      <details>Invalid Font definition, Width of the character "82" in the font program "NNHDHP+Helvetica"is inconsistent with the width in the PDF dictionary.</details>
    </error>
    <error count="2">
      <code>3.1.6</code>
      <details>Invalid Font definition, Width of the character "65" in the font program "NNHDHP+Helvetica"is inconsistent with the width in the PDF dictionary.</details>
    </error>
    <error count="10">
      <code>3.1.6</code>
      <details>Invalid Font definition, Width of the character "101" in the font program "NNHDHP+Helvetica"is inconsistent with the width in the PDF dictionary.</details>
    </error>
    <error count="10">
      <code>3.1.6</code>
      <details>Invalid Font definition, Width of the character "49" in the font program "NNHDHP+Helvetica"is inconsistent with the width in the PDF dictionary.</details>
    </error>
    <error count="2">
      <code>3.1.6</code>
      <details>Invalid Font definition, Width of the character "45" in the font program "NNHDHP+Helvetica"is inconsistent with the width in the PDF dictionary.</details>
    </error>
    <error count="2">
      <code>3.1.6</code>
      <details>Invalid Font definition, Width of the character "55" in the font program "NNHDHP+Helvetica"is inconsistent with the width in the PDF dictionary.</details>
    </error>
    <error count="2">
      <code>3.1.6</code>
      <details>Invalid Font definition, Width of the character "40" in the font program "NNHDHP+Helvetica"is inconsistent with the width in the PDF dictionary.</details>
    </error>
    <error count="4">
      <code>3.1.6</code>
      <details>Invalid Font definition, Width of the character "62" in the font program "NNHDHP+Helvetica"is inconsistent with the width in the PDF dictionary.</details>
    </error>
    <error count="2">
      <code>3.1.6</code>
      <details>Invalid Font definition, Width of the character "41" in the font program "NNHDHP+Helvetica"is inconsistent with the width in the PDF dictionary.</details>
    </error>
    <error count="2">
      <code>3.1.6</code>
      <details>Invalid Font definition, Width of the character "117" in the font program "NNHDHP+Helvetica"is inconsistent with the width in the PDF dictionary.</details>
    </error>
    <error count="4">
      <code>3.1.6</code>
      <details>Invalid Font definition, Width of the character "83" in the font program "NNHDHP+Helvetica"is inconsistent with the width in the PDF dictionary.</details>
    </error>
    <error count="4">
      <code>3.1.6</code>
      <details>Invalid Font definition, Width of the character "69" in the font program "NNHDHP+Helvetica"is inconsistent with the width in the PDF dictionary.</details>
    </error>
    <error count="4">
      <code>3.1.6</code>
      <details>Invalid Font definition, Width of the character "80" in the font program "NNHDHP+Helvetica"is inconsistent with the width in the PDF dictionary.</details>
    </error>
    <error count="1">
      <code>7.11</code>
      <details>Error on MetaData</details>
    </error>
    <error count="13">
      <code>2.3</code>
      <details>Unexpected key in Graphic object definition, No TR key expected in Extended graphics state</details>
    </error>
    <error count="1">
      <code>1.4.6</code>
      <details>Trailer Syntax error, ID is different in the first and the last trailer</details>
    </error>
    <error count="1">
      <code>2.4.3</code>
      <details>Invalid Color space, DestOutputProfile is missing</details>
    </error>
    <error count="16">
      <code>2.4.3</code>
      <details>Invalid Color space, The operator "G" can't be used without Color Profile</details>
    </error>
  </errors>
</preflight>
