<?xml version="1.0" encoding="UTF-8" standalone="no"?>
<preflight name="442595.pdf">
  <executionTimeMS>3004</executionTimeMS>
  <isValid type="PDF/A1-b">false</isValid>
  <errors count="32722">
    <error count="1">
      <code>7.11</code>
      <details>Error on MetaData</details>
    </error>
    <error count="1670">
      <code>2.4.3</code>
      <details>Invalid Color space, The operator "f" can't be used without Color Profile</details>
    </error>
    <error count="732">
      <code>2.4.1</code>
      <details>Invalid Color space, The operator "RG" can't be used with CMYK Profile</details>
    </error>
    <error count="732">
      <code>2.4.1</code>
      <details>Invalid Color space, The operator "rg" can't be used with CMYK Profile</details>
    </error>
    <error count="1">
      <code>3.3.1</code>
      <details>Glyph error, The character "57" in the font program "AAAAAA+Times-New-Roman"is missing from the Charater Encoding.</details>
    </error>
    <error count="1">
      <code>3.3.1</code>
      <details>Glyph error, The character "47" in the font program "AAAAAA+Times-New-Roman"is missing from the Charater Encoding.</details>
    </error>
    <error count="1">
      <code>3.3.1</code>
      <details>Glyph error, The character "74" in the font program "AAAAAA+Times-New-Roman"is missing from the Charater Encoding.</details>
    </error>
    <error count="1">
      <code>3.3.1</code>
      <details>Glyph error, The character "81" in the font program "AAAAAB+Times-New-Roman-Bold"is missing from the Charater Encoding.</details>
    </error>
    <error count="1">
      <code>3.3.1</code>
      <details>Glyph error, The character "79" in the font program "AAAAAB+Times-New-Roman-Bold"is missing from the Charater Encoding.</details>
    </error>
    <error count="2">
      <code>3.3.1</code>
      <details>Glyph error, The character "69" in the font program "AAAAAC+Times-New-Roman-BoldItalic"is missing from the Charater Encoding.</details>
    </error>
    <error count="1">
      <code>3.3.1</code>
      <details>Glyph error, The character "77" in the font program "AAAAAB+Times-New-Roman-Bold"is missing from the Charater Encoding.</details>
    </error>
    <error count="3">
      <code>3.3.1</code>
      <details>Glyph error, The character "43" in the font program "AAAAAA+Times-New-Roman"is missing from the Charater Encoding.</details>
    </error>
    <error count="1">
      <code>3.3.1</code>
      <details>Glyph error, The character "76" in the font program "AAAAAB+Times-New-Roman-Bold"is missing from the Charater Encoding.</details>
    </error>
    <error count="5">
      <code>3.3.1</code>
      <details>Glyph error, The character "42" in the font program "AAAAAA+Times-New-Roman"is missing from the Charater Encoding.</details>
    </error>
    <error count="14">
      <code>3.3.1</code>
      <details>Glyph error, The character "40" in the font program "AAAAAA+Times-New-Roman"is missing from the Charater Encoding.</details>
    </error>
    <error count="1">
      <code>3.3.1</code>
      <details>Glyph error, The character "72" in the font program "AAAAAB+Times-New-Roman-Bold"is missing from the Charater Encoding.</details>
    </error>
    <error count="8">
      <code>3.3.1</code>
      <details>Glyph error, The character "121" in the font program "AAAAAA+Times-New-Roman"is missing from the Charater Encoding.</details>
    </error>
    <error count="2">
      <code>3.3.1</code>
      <details>Glyph error, The character "71" in the font program "AAAAAB+Times-New-Roman-Bold"is missing from the Charater Encoding.</details>
    </error>
    <error count="5">
      <code>3.3.1</code>
      <details>Glyph error, The character "113" in the font program "AAAAAA+Times-New-Roman"is missing from the Charater Encoding.</details>
    </error>
    <error count="5">
      <code>3.3.1</code>
      <details>Glyph error, The character "70" in the font program "AAAAAB+Times-New-Roman-Bold"is missing from the Charater Encoding.</details>
    </error>
    <error count="9">
      <code>3.3.1</code>
      <details>Glyph error, The character "104" in the font program "AAAAAA+Times-New-Roman"is missing from the Charater Encoding.</details>
    </error>
    <error count="18">
      <code>3.3.1</code>
      <details>Glyph error, The character "109" in the font program "AAAAAA+Times-New-Roman"is missing from the Charater Encoding.</details>
    </error>
    <error count="22">
      <code>3.3.1</code>
      <details>Glyph error, The character "86" in the font program "AAAAAA+Times-New-Roman"is missing from the Charater Encoding.</details>
    </error>
    <error count="3">
      <code>3.3.1</code>
      <details>Glyph error, The character "46" in the font program "AAAAAA+Times-New-Roman"is missing from the Charater Encoding.</details>
    </error>
    <error count="15">
      <code>3.3.1</code>
      <details>Glyph error, The character "48" in the font program "AAAAAA+Times-New-Roman"is missing from the Charater Encoding.</details>
    </error>
    <error count="27">
      <code>3.3.1</code>
      <details>Glyph error, The character "103" in the font program "AAAAAA+Times-New-Roman"is missing from the Charater Encoding.</details>
    </error>
    <error count="28">
      <code>3.3.1</code>
      <details>Glyph error, The character "98" in the font program "AAAAAA+Times-New-Roman"is missing from the Charater Encoding.</details>
    </error>
    <error count="77">
      <code>3.3.1</code>
      <details>Glyph error, The character "102" in the font program "AAAAAA+Times-New-Roman"is missing from the Charater Encoding.</details>
    </error>
    <error count="25">
      <code>3.3.1</code>
      <details>Glyph error, The character "117" in the font program "AAAAAA+Times-New-Roman"is missing from the Charater Encoding.</details>
    </error>
    <error count="35">
      <code>3.3.1</code>
      <details>Glyph error, The character "108" in the font program "AAAAAA+Times-New-Roman"is missing from the Charater Encoding.</details>
    </error>
    <error count="204">
      <code>3.3.1</code>
      <details>Glyph error, The character "101" in the font program "AAAAAA+Times-New-Roman"is missing from the Charater Encoding.</details>
    </error>
    <error count="113">
      <code>3.3.1</code>
      <details>Glyph error, The character "34" in the font program "AAAAAA+Times-New-Roman"is missing from the Charater Encoding.</details>
    </error>
    <error count="105">
      <code>3.3.1</code>
      <details>Glyph error, The character "118" in the font program "AAAAAA+Times-New-Roman"is missing from the Charater Encoding.</details>
    </error>
    <error count="1">
      <code>3.3.1</code>
      <details>Glyph error, The character "122" in the font program "AAAAAA+Times-New-Roman"is missing from the Charater Encoding.</details>
    </error>
    <error count="100">
      <code>3.3.1</code>
      <details>Glyph error, The character "78" in the font program "AAAAAA+Times-New-Roman"is missing from the Charater Encoding.</details>
    </error>
    <error count="62">
      <code>3.3.1</code>
      <details>Glyph error, The character "110" in the font program "AAAAAA+Times-New-Roman"is missing from the Charater Encoding.</details>
    </error>
    <error count="71">
      <code>3.3.1</code>
      <details>Glyph error, The character "111" in the font program "AAAAAA+Times-New-Roman"is missing from the Charater Encoding.</details>
    </error>
    <error count="19">
      <code>3.3.1</code>
      <details>Glyph error, The character "90" in the font program "AAAAAA+Times-New-Roman"is missing from the Charater Encoding.</details>
    </error>
    <error count="57">
      <code>3.3.1</code>
      <details>Glyph error, The character "100" in the font program "AAAAAA+Times-New-Roman"is missing from the Charater Encoding.</details>
    </error>
    <error count="307">
      <code>3.3.1</code>
      <details>Glyph error, The character "116" in the font program "AAAAAA+Times-New-Roman"is missing from the Charater Encoding.</details>
    </error>
    <error count="30">
      <code>3.3.1</code>
      <details>Glyph error, The character "112" in the font program "AAAAAA+Times-New-Roman"is missing from the Charater Encoding.</details>
    </error>
    <error count="26">
      <code>3.3.1</code>
      <details>Glyph error, The character "119" in the font program "AAAAAA+Times-New-Roman"is missing from the Charater Encoding.</details>
    </error>
    <error count="97">
      <code>3.3.1</code>
      <details>Glyph error, The character "105" in the font program "AAAAAA+Times-New-Roman"is missing from the Charater Encoding.</details>
    </error>
    <error count="97">
      <code>3.3.1</code>
      <details>Glyph error, The character "91" in the font program "AAAAAA+Times-New-Roman"is missing from the Charater Encoding.</details>
    </error>
    <error count="1350">
      <code>3.3.1</code>
      <details>Glyph error, The character "114" in the font program "AAAAAA+Times-New-Roman"is missing from the Charater Encoding.</details>
    </error>
    <error count="105">
      <code>3.3.1</code>
      <details>Glyph error, The character "86" in the font program "AAAAAB+Times-New-Roman-Bold"is missing from the Charater Encoding.</details>
    </error>
    <error count="119">
      <code>3.3.1</code>
      <details>Glyph error, The character "99" in the font program "AAAAAA+Times-New-Roman"is missing from the Charater Encoding.</details>
    </error>
    <error count="403">
      <code>3.3.1</code>
      <details>Glyph error, The character "66" in the font program "AAAAAA+Times-New-Roman"is missing from the Charater Encoding.</details>
    </error>
    <error count="680">
      <code>3.3.1</code>
      <details>Glyph error, The character "89" in the font program "AAAAAA+Times-New-Roman"is missing from the Charater Encoding.</details>
    </error>
    <error count="249">
      <code>3.3.1</code>
      <details>Glyph error, The character "97" in the font program "AAAAAA+Times-New-Roman"is missing from the Charater Encoding.</details>
    </error>
    <error count="1111">
      <code>3.3.1</code>
      <details>Glyph error, The character "32" in the font program "AAAAAA+Times-New-Roman"is missing from the Charater Encoding.</details>
    </error>
    <error count="551">
      <code>3.3.1</code>
      <details>Glyph error, The character "85" in the font program "AAAAAB+Times-New-Roman-Bold"is missing from the Charater Encoding.</details>
    </error>
    <error count="987">
      <code>3.3.1</code>
      <details>Glyph error, The character "115" in the font program "AAAAAA+Times-New-Roman"is missing from the Charater Encoding.</details>
    </error>
    <error count="550">
      <code>3.3.1</code>
      <details>Glyph error, The character "83" in the font program "AAAAAB+Times-New-Roman-Bold"is missing from the Charater Encoding.</details>
    </error>
    <error count="1048">
      <code>3.3.1</code>
      <details>Glyph error, The character "83" in the font program "AAAAAA+Times-New-Roman"is missing from the Charater Encoding.</details>
    </error>
    <error count="2985">
      <code>3.3.1</code>
      <details>Glyph error, The character "73" in the font program "AAAAAA+Times-New-Roman"is missing from the Charater Encoding.</details>
    </error>
    <error count="1101">
      <code>3.3.1</code>
      <details>Glyph error, The character "82" in the font program "AAAAAB+Times-New-Roman-Bold"is missing from the Charater Encoding.</details>
    </error>
    <error count="551">
      <code>3.3.1</code>
      <details>Glyph error, The character "65" in the font program "AAAAAB+Times-New-Roman-Bold"is missing from the Charater Encoding.</details>
    </error>
    <error count="956">
      <code>3.3.1</code>
      <details>Glyph error, The character "69" in the font program "AAAAAA+Times-New-Roman"is missing from the Charater Encoding.</details>
    </error>
    <error count="1831">
      <code>3.3.1</code>
      <details>Glyph error, The character "80" in the font program "AAAAAA+Times-New-Roman"is missing from the Charater Encoding.</details>
    </error>
    <error count="1">
      <code>3.3.1</code>
      <details>Glyph error, The character "55" in the font program "AAAAAB+Times-New-Roman-Bold"is missing from the Charater Encoding.</details>
    </error>
    <error count="917">
      <code>3.3.1</code>
      <details>Glyph error, The character "68" in the font program "AAAAAA+Times-New-Roman"is missing from the Charater Encoding.</details>
    </error>
    <error count="5">
      <code>3.3.1</code>
      <details>Glyph error, The character "54" in the font program "AAAAAA+Times-New-Roman"is missing from the Charater Encoding.</details>
    </error>
    <error count="642">
      <code>3.3.1</code>
      <details>Glyph error, The character "84" in the font program "AAAAAA+Times-New-Roman"is missing from the Charater Encoding.</details>
    </error>
    <error count="1093">
      <code>3.3.1</code>
      <details>Glyph error, The character "81" in the font program "AAAAAA+Times-New-Roman"is missing from the Charater Encoding.</details>
    </error>
    <error count="53">
      <code>3.3.1</code>
      <details>Glyph error, The character "77" in the font program "AAAAAA+Times-New-Roman"is missing from the Charater Encoding.</details>
    </error>
    <error count="629">
      <code>3.3.1</code>
      <details>Glyph error, The character "76" in the font program "AAAAAA+Times-New-Roman"is missing from the Charater Encoding.</details>
    </error>
    <error count="3">
      <code>3.3.1</code>
      <details>Glyph error, The character "84" in the font program "AAAAAB+Times-New-Roman-Bold"is missing from the Charater Encoding.</details>
    </error>
    <error count="732">
      <code>3.3.1</code>
      <details>Glyph error, The character "52" in the font program "AAAAAA+Times-New-Roman"is missing from the Charater Encoding.</details>
    </error>
    <error count="6">
      <code>3.3.1</code>
      <details>Glyph error, The character "51" in the font program "AAAAAA+Times-New-Roman"is missing from the Charater Encoding.</details>
    </error>
    <error count="9">
      <code>3.3.1</code>
      <details>Glyph error, The character "50" in the font program "AAAAAA+Times-New-Roman"is missing from the Charater Encoding.</details>
    </error>
    <error count="5">
      <code>3.3.1</code>
      <details>Glyph error, The character "53" in the font program "AAAAAA+Times-New-Roman"is missing from the Charater Encoding.</details>
    </error>
    <error count="1540">
      <code>3.3.1</code>
      <details>Glyph error, The character "82" in the font program "AAAAAA+Times-New-Roman"is missing from the Charater Encoding.</details>
    </error>
    <error count="72">
      <code>3.3.1</code>
      <details>Glyph error, The character "72" in the font program "AAAAAA+Times-New-Roman"is missing from the Charater Encoding.</details>
    </error>
    <error count="101">
      <code>3.3.1</code>
      <details>Glyph error, The character "71" in the font program "AAAAAA+Times-New-Roman"is missing from the Charater Encoding.</details>
    </error>
    <error count="1030">
      <code>3.3.1</code>
      <details>Glyph error, The character "70" in the font program "AAAAAA+Times-New-Roman"is missing from the Charater Encoding.</details>
    </error>
    <error count="27">
      <code>3.3.1</code>
      <details>Glyph error, The character "55" in the font program "AAAAAA+Times-New-Roman"is missing from the Charater Encoding.</details>
    </error>
    <error count="1">
      <code>3.3.1</code>
      <details>Glyph error, The character "69" in the font program "AAAAAB+Times-New-Roman-Bold"is missing from the Charater Encoding.</details>
    </error>
    <error count="1121">
      <code>3.3.1</code>
      <details>Glyph error, The character "67" in the font program "AAAAAB+Times-New-Roman-Bold"is missing from the Charater Encoding.</details>
    </error>
    <error count="551">
      <code>3.3.1</code>
      <details>Glyph error, The character "68" in the font program "AAAAAB+Times-New-Roman-Bold"is missing from the Charater Encoding.</details>
    </error>
    <error count="12">
      <code>3.3.1</code>
      <details>Glyph error, The character "87" in the font program "AAAAAA+Times-New-Roman"is missing from the Charater Encoding.</details>
    </error>
    <error count="23">
      <code>3.3.1</code>
      <details>Glyph error, The character "49" in the font program "AAAAAA+Times-New-Roman"is missing from the Charater Encoding.</details>
    </error>
    <error count="960">
      <code>3.3.1</code>
      <details>Glyph error, The character "65" in the font program "AAAAAA+Times-New-Roman"is missing from the Charater Encoding.</details>
    </error>
    <error count="2878">
      <code>3.3.1</code>
      <details>Glyph error, The character "67" in the font program "AAAAAA+Times-New-Roman"is missing from the Charater Encoding.</details>
    </error>
    <error count="908">
      <code>3.3.1</code>
      <details>Glyph error, The character "79" in the font program "AAAAAA+Times-New-Roman"is missing from the Charater Encoding.</details>
    </error>
    <error count="91">
      <code>3.3.1</code>
      <details>Glyph error, The character "85" in the font program "AAAAAA+Times-New-Roman"is missing from the Charater Encoding.</details>
    </error>
  </errors>
</preflight>
