<?xml version="1.0" encoding="UTF-8" standalone="no"?>
<preflight name="516859.pdf">
  <executionTimeMS>2304</executionTimeMS>
  <isValid type="PDF/A1-b">false</isValid>
  <errors count="3275">
    <error count="2">
      <code>3.1.5</code>
      <details>Invalid Font definition, The Encoding should be missing for the Symbolic TTF</details>
    </error>
    <error count="2">
      <code>3.1.6</code>
      <details>Invalid Font definition, Width of the character "32" in the font program "HPLTSK+Times-Roman?~182"is inconsistent with the width in the PDF dictionary.</details>
    </error>
    <error count="1">
      <code>3.1.6</code>
      <details>Invalid Font definition, Width of the character "32" in the font program "TPOVRQ+Helvetica?~17a"is inconsistent with the width in the PDF dictionary.</details>
    </error>
    <error count="1">
      <code>3.1.6</code>
      <details>Invalid Font definition, Width of the character "32" in the font program "AOLSMX+Helvetica?~169"is inconsistent with the width in the PDF dictionary.</details>
    </error>
    <error count="4">
      <code>3.1.6</code>
      <details>Invalid Font definition, Width of the character "32" in the font program "BGKWCI+Times-Roman?~166"is inconsistent with the width in the PDF dictionary.</details>
    </error>
    <error count="62">
      <code>3.1.6</code>
      <details>Invalid Font definition, Width of the character "32" in the font program "KWXTEW+Helvetica?~15b"is inconsistent with the width in the PDF dictionary.</details>
    </error>
    <error count="29">
      <code>3.1.6</code>
      <details>Invalid Font definition, Width of the character "32" in the font program "HMIPHE+Times-Roman?~158"is inconsistent with the width in the PDF dictionary.</details>
    </error>
    <error count="2">
      <code>3.1.6</code>
      <details>Invalid Font definition, Width of the character "120" in the font program "ASLJWX+Helvetica?~149"is inconsistent with the width in the PDF dictionary.</details>
    </error>
    <error count="2">
      <code>3.1.6</code>
      <details>Invalid Font definition, Width of the character "121" in the font program "ASLJWX+Helvetica?~149"is inconsistent with the width in the PDF dictionary.</details>
    </error>
    <error count="2">
      <code>3.1.6</code>
      <details>Invalid Font definition, Width of the character "98" in the font program "ASLJWX+Helvetica?~149"is inconsistent with the width in the PDF dictionary.</details>
    </error>
    <error count="6">
      <code>3.1.6</code>
      <details>Invalid Font definition, Width of the character "110" in the font program "ASLJWX+Helvetica?~149"is inconsistent with the width in the PDF dictionary.</details>
    </error>
    <error count="20">
      <code>3.1.6</code>
      <details>Invalid Font definition, Width of the character "32" in the font program "DCBOTP+Helvetica??~14c"is inconsistent with the width in the PDF dictionary.</details>
    </error>
    <error count="6">
      <code>3.1.6</code>
      <details>Invalid Font definition, Width of the character "114" in the font program "ASLJWX+Helvetica?~149"is inconsistent with the width in the PDF dictionary.</details>
    </error>
    <error count="4">
      <code>3.1.6</code>
      <details>Invalid Font definition, Width of the character "108" in the font program "ASLJWX+Helvetica?~149"is inconsistent with the width in the PDF dictionary.</details>
    </error>
    <error count="2">
      <code>3.1.6</code>
      <details>Invalid Font definition, Width of the character "104" in the font program "ASLJWX+Helvetica?~149"is inconsistent with the width in the PDF dictionary.</details>
    </error>
    <error count="4">
      <code>3.1.6</code>
      <details>Invalid Font definition, Width of the character "100" in the font program "ASLJWX+Helvetica?~149"is inconsistent with the width in the PDF dictionary.</details>
    </error>
    <error count="4">
      <code>3.1.6</code>
      <details>Invalid Font definition, Width of the character "32" in the font program "ASLJWX+Helvetica?~149"is inconsistent with the width in the PDF dictionary.</details>
    </error>
    <error count="4">
      <code>3.1.6</code>
      <details>Invalid Font definition, Width of the character "116" in the font program "ASLJWX+Helvetica?~149"is inconsistent with the width in the PDF dictionary.</details>
    </error>
    <error count="6">
      <code>3.1.6</code>
      <details>Invalid Font definition, Width of the character "111" in the font program "ASLJWX+Helvetica?~149"is inconsistent with the width in the PDF dictionary.</details>
    </error>
    <error count="6">
      <code>3.1.6</code>
      <details>Invalid Font definition, Width of the character "105" in the font program "ASLJWX+Helvetica?~149"is inconsistent with the width in the PDF dictionary.</details>
    </error>
    <error count="2">
      <code>3.1.6</code>
      <details>Invalid Font definition, Width of the character "66" in the font program "ASLJWX+Helvetica?~149"is inconsistent with the width in the PDF dictionary.</details>
    </error>
    <error count="1">
      <code>3.1.6</code>
      <details>Invalid Font definition, Width of the character "32" in the font program "XHWEZF+Times-Roman?~146"is inconsistent with the width in the PDF dictionary.</details>
    </error>
    <error count="1">
      <code>3.1.6</code>
      <details>Invalid Font definition, Width of the character "66" in the font program "HQIGRE+Helvetica??~138"is inconsistent with the width in the PDF dictionary.</details>
    </error>
    <error count="2">
      <code>3.1.6</code>
      <details>Invalid Font definition, Width of the character "116" in the font program "HQIGRE+Helvetica??~138"is inconsistent with the width in the PDF dictionary.</details>
    </error>
    <error count="1">
      <code>3.1.6</code>
      <details>Invalid Font definition, Width of the character "104" in the font program "HQIGRE+Helvetica??~138"is inconsistent with the width in the PDF dictionary.</details>
    </error>
    <error count="1">
      <code>3.1.6</code>
      <details>Invalid Font definition, Width of the character "109" in the font program "HQIGRE+Helvetica??~138"is inconsistent with the width in the PDF dictionary.</details>
    </error>
    <error count="1">
      <code>3.1.6</code>
      <details>Invalid Font definition, Width of the character "32" in the font program "HQIGRE+Helvetica??~138"is inconsistent with the width in the PDF dictionary.</details>
    </error>
    <error count="1">
      <code>3.1.6</code>
      <details>Invalid Font definition, Width of the character "32" in the font program "WABNNC+Helvetica?~133"is inconsistent with the width in the PDF dictionary.</details>
    </error>
    <error count="5">
      <code>3.1.6</code>
      <details>Invalid Font definition, Width of the character "32" in the font program "TQLIQK+Times-Roman?~130"is inconsistent with the width in the PDF dictionary.</details>
    </error>
    <error count="3">
      <code>3.1.6</code>
      <details>Invalid Font definition, Width of the character "115" in the font program "BHHJBC+Helvetica??~11c"is inconsistent with the width in the PDF dictionary.</details>
    </error>
    <error count="3">
      <code>3.1.6</code>
      <details>Invalid Font definition, Width of the character "75" in the font program "BHHJBC+Helvetica??~11c"is inconsistent with the width in the PDF dictionary.</details>
    </error>
    <error count="3">
      <code>3.1.6</code>
      <details>Invalid Font definition, Width of the character "108" in the font program "BHHJBC+Helvetica??~11c"is inconsistent with the width in the PDF dictionary.</details>
    </error>
    <error count="3">
      <code>3.1.6</code>
      <details>Invalid Font definition, Width of the character "66" in the font program "BHHJBC+Helvetica??~11c"is inconsistent with the width in the PDF dictionary.</details>
    </error>
    <error count="6">
      <code>3.1.6</code>
      <details>Invalid Font definition, Width of the character "109" in the font program "BHHJBC+Helvetica??~11c"is inconsistent with the width in the PDF dictionary.</details>
    </error>
    <error count="1">
      <code>3.1.6</code>
      <details>Invalid Font definition, Width of the character "32" in the font program "TULZZK+Times-Roman?~110"is inconsistent with the width in the PDF dictionary.</details>
    </error>
    <error count="40">
      <code>3.1.6</code>
      <details>Invalid Font definition, Width of the character "32" in the font program "CLZWBZ+Times-Roman?~105"is inconsistent with the width in the PDF dictionary.</details>
    </error>
    <error count="50">
      <code>3.1.6</code>
      <details>Invalid Font definition, Width of the character "32" in the font program "DDYASJ+Helvetica?~102"is inconsistent with the width in the PDF dictionary.</details>
    </error>
    <error count="2">
      <code>3.1.6</code>
      <details>Invalid Font definition, Width of the character "32" in the font program "VQCRQS+Helvetica?~f6"is inconsistent with the width in the PDF dictionary.</details>
    </error>
    <error count="2">
      <code>3.1.6</code>
      <details>Invalid Font definition, Width of the character "32" in the font program "BEEFQV+Times-Roman?~f2"is inconsistent with the width in the PDF dictionary.</details>
    </error>
    <error count="2">
      <code>3.1.6</code>
      <details>Invalid Font definition, Width of the character "32" in the font program "TRIVOE+Times-Roman?"is inconsistent with the width in the PDF dictionary.</details>
    </error>
    <error count="33">
      <code>3.1.6</code>
      <details>Invalid Font definition, Width of the character "32" in the font program "ZEKJOH+Helvetica??~e2"is inconsistent with the width in the PDF dictionary.</details>
    </error>
    <error count="1">
      <code>3.1.6</code>
      <details>Invalid Font definition, Width of the character "105" in the font program "AXINES+Helvetica?~df"is inconsistent with the width in the PDF dictionary.</details>
    </error>
    <error count="31">
      <code>3.1.6</code>
      <details>Invalid Font definition, Width of the character "32" in the font program "AQFSJL+Helvetica?~d5"is inconsistent with the width in the PDF dictionary.</details>
    </error>
    <error count="47">
      <code>3.1.6</code>
      <details>Invalid Font definition, Width of the character "32" in the font program "ELQFCH+Helvetica?~cb"is inconsistent with the width in the PDF dictionary.</details>
    </error>
    <error count="42">
      <code>3.1.6</code>
      <details>Invalid Font definition, Width of the character "32" in the font program "IGBTUC+Helvetica?~c1"is inconsistent with the width in the PDF dictionary.</details>
    </error>
    <error count="1">
      <code>3.1.6</code>
      <details>Invalid Font definition, Width of the character "102" in the font program "RWOQWQ+Helvetica??~b6"is inconsistent with the width in the PDF dictionary.</details>
    </error>
    <error count="1">
      <code>3.1.6</code>
      <details>Invalid Font definition, Width of the character "32" in the font program "RWOQWQ+Helvetica??~b6"is inconsistent with the width in the PDF dictionary.</details>
    </error>
    <error count="1">
      <code>3.1.6</code>
      <details>Invalid Font definition, Width of the character "108" in the font program "RWOQWQ+Helvetica??~b6"is inconsistent with the width in the PDF dictionary.</details>
    </error>
    <error count="1">
      <code>3.1.6</code>
      <details>Invalid Font definition, Width of the character "65" in the font program "RWOQWQ+Helvetica??~b6"is inconsistent with the width in the PDF dictionary.</details>
    </error>
    <error count="45">
      <code>3.1.6</code>
      <details>Invalid Font definition, Width of the character "32" in the font program "OMZLZY+Helvetica?~b3"is inconsistent with the width in the PDF dictionary.</details>
    </error>
    <error count="3">
      <code>3.1.6</code>
      <details>Invalid Font definition, Width of the character "32" in the font program "BFBSOP+Helvetica-Oblique?~a8"is inconsistent with the width in the PDF dictionary.</details>
    </error>
    <error count="63">
      <code>3.1.6</code>
      <details>Invalid Font definition, Width of the character "32" in the font program "YULNRX+Helvetica?~a5"is inconsistent with the width in the PDF dictionary.</details>
    </error>
    <error count="96">
      <code>3.1.6</code>
      <details>Invalid Font definition, Width of the character "32" in the font program "LNNTGO+Helvetica?~9a"is inconsistent with the width in the PDF dictionary.</details>
    </error>
    <error count="1">
      <code>3.1.6</code>
      <details>Invalid Font definition, Width of the character "32" in the font program "DBSJFX+Helvetica-Oblique?~8e"is inconsistent with the width in the PDF dictionary.</details>
    </error>
    <error count="1">
      <code>3.1.6</code>
      <details>Invalid Font definition, Width of the character "105" in the font program "ARCFIF+Helvetica??~8b"is inconsistent with the width in the PDF dictionary.</details>
    </error>
    <error count="1">
      <code>3.1.6</code>
      <details>Invalid Font definition, Width of the character "32" in the font program "ARCFIF+Helvetica??~8b"is inconsistent with the width in the PDF dictionary.</details>
    </error>
    <error count="89">
      <code>3.1.6</code>
      <details>Invalid Font definition, Width of the character "32" in the font program "BJBJYP+Helvetica?~88"is inconsistent with the width in the PDF dictionary.</details>
    </error>
    <error count="1">
      <code>3.1.6</code>
      <details>Invalid Font definition, Width of the character "32" in the font program "KZOGAE+Helvetica-Oblique?~7d"is inconsistent with the width in the PDF dictionary.</details>
    </error>
    <error count="39">
      <code>3.1.6</code>
      <details>Invalid Font definition, Width of the character "32" in the font program "HPZBDM+Helvetica?~7a"is inconsistent with the width in the PDF dictionary.</details>
    </error>
    <error count="1">
      <code>3.1.6</code>
      <details>Invalid Font definition, Width of the character "32" in the font program "UHBISC+Helvetica-Oblique?~6f"is inconsistent with the width in the PDF dictionary.</details>
    </error>
    <error count="37">
      <code>3.1.6</code>
      <details>Invalid Font definition, Width of the character "32" in the font program "RXLDVK+Helvetica?~6c"is inconsistent with the width in the PDF dictionary.</details>
    </error>
    <error count="1">
      <code>3.1.6</code>
      <details>Invalid Font definition, Width of the character "105" in the font program "JLQTTT+Helvetica??~60"is inconsistent with the width in the PDF dictionary.</details>
    </error>
    <error count="1">
      <code>3.1.6</code>
      <details>Invalid Font definition, Width of the character "116" in the font program "JLQTTT+Helvetica??~60"is inconsistent with the width in the PDF dictionary.</details>
    </error>
    <error count="1">
      <code>3.1.6</code>
      <details>Invalid Font definition, Width of the character "65" in the font program "JLQTTT+Helvetica??~60"is inconsistent with the width in the PDF dictionary.</details>
    </error>
    <error count="3">
      <code>3.1.6</code>
      <details>Invalid Font definition, Width of the character "32" in the font program "KDPXJE+Helvetica-Oblique?~5d"is inconsistent with the width in the PDF dictionary.</details>
    </error>
    <error count="44">
      <code>3.1.6</code>
      <details>Invalid Font definition, Width of the character "32" in the font program "EJKOPU+Helvetica?~57"is inconsistent with the width in the PDF dictionary.</details>
    </error>
    <error count="1">
      <code>3.1.6</code>
      <details>Invalid Font definition, Width of the character "32" in the font program "AZCNBG+Helvetica-Oblique?"is inconsistent with the width in the PDF dictionary.</details>
    </error>
    <error count="1">
      <code>3.1.6</code>
      <details>Invalid Font definition, Width of the character "105" in the font program "XONIEO+Helvetica??~48"is inconsistent with the width in the PDF dictionary.</details>
    </error>
    <error count="1">
      <code>3.1.6</code>
      <details>Invalid Font definition, Width of the character "116" in the font program "XONIEO+Helvetica??~48"is inconsistent with the width in the PDF dictionary.</details>
    </error>
    <error count="1">
      <code>3.1.6</code>
      <details>Invalid Font definition, Width of the character "65" in the font program "XONIEO+Helvetica??~48"is inconsistent with the width in the PDF dictionary.</details>
    </error>
    <error count="40">
      <code>3.1.6</code>
      <details>Invalid Font definition, Width of the character "32" in the font program "UEYDHW+Helvetica?~45"is inconsistent with the width in the PDF dictionary.</details>
    </error>
    <error count="1">
      <code>3.1.6</code>
      <details>Invalid Font definition, Width of the character "32" in the font program "HXZJWM+Helvetica??~3a"is inconsistent with the width in the PDF dictionary.</details>
    </error>
    <error count="1">
      <code>3.1.6</code>
      <details>Invalid Font definition, Width of the character "111" in the font program "HXZJWM+Helvetica??~3a"is inconsistent with the width in the PDF dictionary.</details>
    </error>
    <error count="45">
      <code>3.1.6</code>
      <details>Invalid Font definition, Width of the character "32" in the font program "ENKFZU+Helvetica?~37"is inconsistent with the width in the PDF dictionary.</details>
    </error>
    <error count="1">
      <code>3.1.6</code>
      <details>Invalid Font definition, Width of the character "32" in the font program "NDYCBJ+Helvetica??~2c"is inconsistent with the width in the PDF dictionary.</details>
    </error>
    <error count="1">
      <code>3.1.6</code>
      <details>Invalid Font definition, Width of the character "116" in the font program "NDYCBJ+Helvetica??~2c"is inconsistent with the width in the PDF dictionary.</details>
    </error>
    <error count="1">
      <code>3.1.6</code>
      <details>Invalid Font definition, Width of the character "115" in the font program "NDYCBJ+Helvetica??~2c"is inconsistent with the width in the PDF dictionary.</details>
    </error>
    <error count="1">
      <code>3.1.6</code>
      <details>Invalid Font definition, Width of the character "114" in the font program "NDYCBJ+Helvetica??~2c"is inconsistent with the width in the PDF dictionary.</details>
    </error>
    <error count="51">
      <code>3.1.6</code>
      <details>Invalid Font definition, Width of the character "32" in the font program "OVWGRT+Helvetica?~29"is inconsistent with the width in the PDF dictionary.</details>
    </error>
    <error count="1">
      <code>3.1.6</code>
      <details>Invalid Font definition, Width of the character "110" in the font program "XLKETH+Helvetica??~1e"is inconsistent with the width in the PDF dictionary.</details>
    </error>
    <error count="53">
      <code>3.1.6</code>
      <details>Invalid Font definition, Width of the character "32" in the font program "UBVZVP+Helvetica?~1b"is inconsistent with the width in the PDF dictionary.</details>
    </error>
    <error count="1">
      <code>3.1.6</code>
      <details>Invalid Font definition, Width of the character "65" in the font program "KXIPNR+Helvetica?"is inconsistent with the width in the PDF dictionary.</details>
    </error>
    <error count="1">
      <code>3.1.6</code>
      <details>Invalid Font definition, Width of the character "65" in the font program "QRNYHB+Helvetica???"is inconsistent with the width in the PDF dictionary.</details>
    </error>
    <error count="1">
      <code>3.1.6</code>
      <details>Invalid Font definition, Width of the character "57" in the font program "QRNYHB+Helvetica???"is inconsistent with the width in the PDF dictionary.</details>
    </error>
    <error count="1">
      <code>3.1.6</code>
      <details>Invalid Font definition, Width of the character "99" in the font program "QRNYHB+Helvetica???"is inconsistent with the width in the PDF dictionary.</details>
    </error>
    <error count="1">
      <code>3.1.6</code>
      <details>Invalid Font definition, Width of the character "84" in the font program "QRNYHB+Helvetica???"is inconsistent with the width in the PDF dictionary.</details>
    </error>
    <error count="43">
      <code>3.1.6</code>
      <details>Invalid Font definition, Width of the character "32" in the font program "NHYTKJ+Helvetica??"is inconsistent with the width in the PDF dictionary.</details>
    </error>
    <error count="2">
      <code>3.1.6</code>
      <details>Invalid Font definition, Width of the character "105" in the font program "KXIPNR+Helvetica?"is inconsistent with the width in the PDF dictionary.</details>
    </error>
    <error count="1">
      <code>3.1.6</code>
      <details>Invalid Font definition, Width of the character "115" in the font program "KXIPNR+Helvetica?"is inconsistent with the width in the PDF dictionary.</details>
    </error>
    <error count="1">
      <code>3.1.6</code>
      <details>Invalid Font definition, Width of the character "32" in the font program "KXIPNR+Helvetica?"is inconsistent with the width in the PDF dictionary.</details>
    </error>
    <error count="1">
      <code>3.1.6</code>
      <details>Invalid Font definition, Width of the character "110" in the font program "KXIPNR+Helvetica?"is inconsistent with the width in the PDF dictionary.</details>
    </error>
    <error count="1">
      <code>3.1.6</code>
      <details>Invalid Font definition, Width of the character "121" in the font program "KXIPNR+Helvetica?"is inconsistent with the width in the PDF dictionary.</details>
    </error>
    <error count="7">
      <code>1.0.12</code>
      <details>Syntax error, Hexa String must have only Hexadecimal Characters (found '
')</details>
    </error>
    <error count="8">
      <code>1.2.1</code>
      <details>Body Syntax error, EOL expected before the 'endobj' keyword</details>
    </error>
    <error count="24">
      <code>1.2.2</code>
      <details>Body Syntax error, Expected 'EOL' before the endstream keyword</details>
    </error>
    <error count="85">
      <code>1.2.5</code>
      <details>Body Syntax error, Stream length is invalide</details>
    </error>
    <error count="1">
      <code>7.1</code>
      <details>Error on MetaData, Missing Metadata Key in catalog</details>
    </error>
    <error count="1">
      <code>1.4.1</code>
      <details>Trailer Syntax error, The trailer dictionary doesn't contain ID</details>
    </error>
    <error count="1417">
      <code>2.4.3</code>
      <details>Invalid Color space, The operator "f*" can't be used without Color Profile</details>
    </error>
    <error count="110">
      <code>2.4.3</code>
      <details>Invalid Color space, The operator "G" can't be used without Color Profile</details>
    </error>
    <error count="15">
      <code>2.4.3</code>
      <details>Invalid Color space, DestOutputProfile is missing</details>
    </error>
    <error count="187">
      <code>2.4.3</code>
      <details>Invalid Color space, The operator "f" can't be used without Color Profile</details>
    </error>
    <error count="277">
      <code>2.4.3</code>
      <details>Invalid Color space, The operator "g" can't be used without Color Profile</details>
    </error>
    <error count="5">
      <code>2.4.1</code>
      <details>Invalid Color space, The operator "rg" can't be used with CMYK Profile</details>
    </error>
  </errors>
</preflight>
